pskit/__init__.py
pskit/base.py
pskit/models.py
pskit/pipeline.py
pskit/simple_models.py
pskit/transformers.py
pskit/tree_models.py
pskit/trees.py
pskit-0.0.5.dist-info/LICENSE
pskit-0.0.5.dist-info/METADATA
pskit-0.0.5.dist-info/WHEEL
pskit-0.0.5.dist-info/top_level.txt
pskit-0.0.5.dist-info/RECORD
