Metadata-Version: 2.1
Name: pskit
Version: 0.0.5
Summary: Toolkit for an easy use of pandas, sklearn and popular ml libraries
Home-page: https://github.com/trantrikien239/pandas-sklearn-toolkit
Author: Kien Tran
Author-email: trantrikien239@gmail.com
License: MIT
Platform: UNKNOWN
Classifier: License :: OSI Approved :: MIT License
Classifier: Programming Language :: Python :: 3.7
Classifier: Programming Language :: Python :: 3.8
License-File: LICENSE
Requires-Dist: pandas
Requires-Dist: numpy
Requires-Dist: scikit-learn
Requires-Dist: catboost
